{
    "swagger": "2.0",
    "info": {
        "contact": {}
    },
    "basePath": "/",
    "paths": {
        "/email-change": {
            "post": {
                "description": "send an email-change verification email to a user",
                "consumes": [
                    "application/json"
                ],
                "produces": [
                    "application/json"
                ],
                "tags": [
                    "email"
                ],
                "summary": "Send Email Change Verification Email",
                "parameters": [
                    {
                        "description": "Email Change Info",
                        "name": "emailChange",
                        "in": "body",
                        "required": true,
                        "schema": {
                            "$ref": "#/definitions/routes.EmailChangeRequest"
                        }
                    }
                ],
                "responses": {
                    "200": {
                        "description": "OK",
                        "schema": {
                            "type": "object",
                            "additionalProperties": {
                                "type": "string"
                            }
                        }
                    }
                }
            }
        },
        "/health": {
            "get": {
                "description": "get the health status",
                "consumes": [
                    "application/json"
                ],
                "produces": [
                    "application/json"
                ],
                "tags": [
                    "health"
                ],
                "summary": "Health Check",
                "responses": {
                    "200": {
                        "description": "OK",
                        "schema": {
                            "type": "object",
                            "additionalProperties": {
                                "type": "string"
                            }
                        }
                    }
                }
            }
        },
        "/register": {
            "post": {
                "description": "send a registration email to a new user",
                "consumes": [
                    "application/json"
                ],
                "produces": [
                    "application/json"
                ],
                "tags": [
                    "registration"
                ],
                "summary": "Send Registration Email",
                "parameters": [
                    {
                        "description": "Registration Info",
                        "name": "registration",
                        "in": "body",
                        "required": true,
                        "schema": {
                            "$ref": "#/definitions/routes.RegistrationRequest"
                        }
                    }
                ],
                "responses": {
                    "200": {
                        "description": "OK",
                        "schema": {
                            "type": "object",
                            "additionalProperties": {
                                "type": "string"
                            }
                        }
                    }
                }
            }
        }
    },
    "definitions": {
        "routes.EmailChangeRequest": {
            "type": "object",
            "properties": {
                "code": {
                    "type": "string"
                },
                "email": {
                    "type": "string"
                },
                "name": {
                    "type": "string"
                }
            }
        },
        "routes.RegistrationRequest": {
            "type": "object",
            "properties": {
                "code": {
                    "type": "string"
                },
                "email": {
                    "type": "string"
                },
                "name": {
                    "type": "string"
                }
            }
        }
    }
}